disk_treemap/Everything64.dll
disk_treemap/Everything_license.txt
disk_treemap/__init__.py
disk_treemap/main.py
disk_treemap/scan_everything.py
disk_treemap/scan_fs.py
disk_treemap/scan_s3.py
disk_treemap/static/dist/webapp/3rdpartylicenses.txt
disk_treemap/static/dist/webapp/favicon.ico
disk_treemap/static/dist/webapp/index.html
disk_treemap/static/dist/webapp/main.5cc76c324311214514de.js
disk_treemap/static/dist/webapp/polyfills.aff2eefe283ca9600825.js
disk_treemap/static/dist/webapp/runtime.ae823e292a77cd950d0a.js
disk_treemap/static/dist/webapp/styles.fd7e0e557b99d505e7ac.css
disk_treemap-1.0.10.dist-info/LICENSE
disk_treemap-1.0.10.dist-info/METADATA
disk_treemap-1.0.10.dist-info/WHEEL
disk_treemap-1.0.10.dist-info/entry_points.txt
disk_treemap-1.0.10.dist-info/top_level.txt
disk_treemap-1.0.10.dist-info/zip-safe
disk_treemap-1.0.10.dist-info/RECORD
