Metadata-Version: 2.1
Name: disk-treemap
Version: 1.0.10
Summary: Just another disk usage analyzer with treemap GUI.
Home-page: https://github.com/exzhawk/disk_treemap
Author: Epix Zhang
License: MIT
Classifier: Programming Language :: Python :: 3
Classifier: License :: OSI Approved :: MIT License
Classifier: Operating System :: OS Independent
Classifier: Development Status :: 5 - Production/Stable
Classifier: Environment :: Console
Classifier: Environment :: Web Environment
Classifier: Framework :: Flask
Classifier: Intended Audience :: End Users/Desktop
Classifier: Intended Audience :: System Administrators
Classifier: Programming Language :: JavaScript
Classifier: Topic :: Desktop Environment :: File Managers
Classifier: Topic :: Scientific/Engineering :: Visualization
Classifier: Topic :: System :: Filesystems
Classifier: Topic :: Utilities
Requires-Python: >=3.6
License-File: LICENSE
Requires-Dist: flask (>=2.0)
Requires-Dist: tqdm
Requires-Dist: flask-compress
Requires-Dist: boto3
